quick_start-0.0.dev10.data/data/sample.zip
quick_start-0.0.dev10.data/scripts/quickstart_installer
quickstart/__init__.py
quickstart/__main__.py
quickstart/config.py
quick_start-0.0.dev10.dist-info/METADATA
quick_start-0.0.dev10.dist-info/WHEEL
quick_start-0.0.dev10.dist-info/entry_points.txt
quick_start-0.0.dev10.dist-info/top_level.txt
quick_start-0.0.dev10.dist-info/RECORD
