Metadata-Version: 2.1
Name: quick-start
Version: 0.0.dev10
Summary: My short description for my project.
Home-page: http://github.com/andreztz/quick-start
Author: André Pereira dos Santos
Author-email: andreztz@gmail.com
License: MIT
Keywords: quick start project
Platform: UNKNOWN
Classifier: Development Status :: 1 - Planning
Classifier: Environment :: Console
Classifier: Programming Language :: Python :: 3
Classifier: Operating System :: OS Independent
Classifier: Intended Audience :: Developers
Requires-Python: >=3.7.0
Requires-Dist: Click (==7.0)
Requires-Dist: appdirs (==1.4.3)
